img2catalog/__about__.py
img2catalog/__init__.py
img2catalog/__main__.py
img2catalog/cli_app.py
img2catalog/configmanager.py
img2catalog/const.py
img2catalog/logger.py
img2catalog/inputs/__init__.py
img2catalog/inputs/config.py
img2catalog/inputs/xnat.py
img2catalog/mappings/__init__.py
img2catalog/mappings/xnat.py
img2catalog/outputs/__init__.py
img2catalog/outputs/fdp.py
img2catalog/outputs/rdf.py
img2catalog-2.0.0.dist-info/METADATA
img2catalog-2.0.0.dist-info/WHEEL
img2catalog-2.0.0.dist-info/entry_points.txt
img2catalog-2.0.0.dist-info/licenses/LICENSE.md
img2catalog-2.0.0.dist-info/RECORD
