Metadata-Version: 2.4
Name: img2catalog
Version: 2.0.0
Summary: This tool generates RDF metadata from medical imaging respositories
Project-URL: Documentation, https://github.com/health-ri/img2catalog#readme
Project-URL: Issues, https://github.com/health-ri/img2catalog/issues
Project-URL: Source, https://github.com/health-ri/img2catalog
Author-email: Mark Janse <mark.janse@health-ri.nl>
License: MIT License
License-File: LICENSE.md
Classifier: Development Status :: 4 - Beta
Classifier: Programming Language :: Python
Classifier: Programming Language :: Python :: 3.8
Classifier: Programming Language :: Python :: 3.9
Classifier: Programming Language :: Python :: 3.10
Classifier: Programming Language :: Python :: 3.11
Classifier: Programming Language :: Python :: 3.12
Classifier: Programming Language :: Python :: Implementation :: CPython
Classifier: Programming Language :: Python :: Implementation :: PyPy
Requires-Python: >=3.8
Requires-Dist: click-option-group~=0.5.6
Requires-Dist: click>=8.0.0
Requires-Dist: fairclient>=1.0.0
Requires-Dist: rdflib<7.2,>=7.0
Requires-Dist: sempyro>=2.0.3
Requires-Dist: sparqlwrapper~=2.0
Requires-Dist: tomli>=1.10; python_version < '3.11'
Requires-Dist: tqdm>=4.21
Requires-Dist: xnat~=0.6
